Metadata-Version: 2.1
Name: django2-semantic-ui
Version: 1.0.1
Summary: Library to easy install, configure and use Semantic UI framework with Django project (Python 3.x)
Home-page: https://github.com/franklintiel/django2-semantic-ui/wiki
Author: Franklin Sarmiento
Author-email: franklinitiel@gmail.com
License: MIT
Project-URL: Documentation, https://github.com/franklintiel/django2-semantic-ui
Project-URL: Source, https://github.com/franklintiel/django2-semantic-ui
Project-URL: Tracker, https://github.com/franklintiel/django2-semantic-ui/issues
Keywords: semantic-ui semanticui semantic ui django-semantic-ui django-semanticui django-semantic-ui
Platform: UNKNOWN
Classifier: Development Status :: 5 - Production/Stable
Classifier: License :: OSI Approved :: MIT License
Classifier: Programming Language :: Python :: 3.6
Requires-Python: >=3.*
